cli/__init__.py
cli/helpers.py
cli/main.py
orchestry-1.0.1.dist-info/licenses/LICENSE
orchestry-1.0.1.dist-info/METADATA
orchestry-1.0.1.dist-info/WHEEL
orchestry-1.0.1.dist-info/entry_points.txt
orchestry-1.0.1.dist-info/top_level.txt
orchestry-1.0.1.dist-info/RECORD
