Metadata-Version: 2.4
Name: orchestry
Version: 1.0.1
Summary: Orchestry - Automatic orchestration, scaling and load balancing for containerized applications
Author-email: Hemanth S Banur <arjunbanur27@gmail.com>
License-Expression: GPL-3.0-or-later
Project-URL: Homepage, https://arjuuuuunnnnn.github.io/Orchestry/
Project-URL: Repository, https://github.com/arjuuuuunnnnn/Orchestry
Classifier: Development Status :: 4 - Beta
Classifier: Intended Audience :: Developers
Classifier: Programming Language :: Python :: 3.9
Classifier: Programming Language :: Python :: 3.10
Classifier: Programming Language :: Python :: 3.11
Classifier: Programming Language :: Python :: 3.12
Classifier: Programming Language :: Python :: 3.13
Requires-Python: >=3.8
License-File: LICENSE
Requires-Dist: typer==0.17.4
Requires-Dist: requests==2.32.5
Requires-Dist: python-dotenv==1.1.1
Requires-Dist: pyyaml==6.0.2
Requires-Dist: platformdirs==4.4.0
Dynamic: license-file
